README.md
setup.cfg
setup.py
rdap/__init__.py
rdap/rdap.py
rdap/settings.py
rdap/commands/__init__.py
rdap/commands/check/__init__.py
rdap/commands/check/check.py
rdap/commands/gather/__init__.py
rdap/commands/gather/exceptions.py
rdap/commands/gather/gather.py
rdap/commands/gather/utils.py
rdap/commands/history/__init__.py
rdap/commands/history/history.py
rdap/commands/history/utils.py
rdap/commands/settings/__init__.py
rdap/commands/settings/cli_settings.py
rdap/commands/version/__init__.py
rdap/commands/version/version.py
rdap/common/__init__.py
rdap/common/constants.py
rdap/common/endpoints.py
rdap/common/exceptions.py
rdap/common/save.py
rdap/common/utils.py
rdap/services/__init__.py
rdap/services/rdap.py
rdap/services/rdap_client.py
rdap_cli.egg-info/PKG-INFO
rdap_cli.egg-info/SOURCES.txt
rdap_cli.egg-info/dependency_links.txt
rdap_cli.egg-info/entry_points.txt
rdap_cli.egg-info/requires.txt
rdap_cli.egg-info/top_level.txt